core.py
gemini_cli_wrapper-0.1.0.dist-info/METADATA
gemini_cli_wrapper-0.1.0.dist-info/WHEEL
gemini_cli_wrapper-0.1.0.dist-info/top_level.txt
gemini_cli_wrapper-0.1.0.dist-info/RECORD
