Metadata-Version: 2.4
Name: gemini-cli-wrapper
Version: 0.1.0
Summary: Простая Python-оболочка для утилиты командной строки Google Gemini.
Author-email: nousernameai <azureopenaidsfsdf86@gmail.com>
Classifier: Programming Language :: Python :: 3
Classifier: License :: OSI Approved :: MIT License
Classifier: Operating System :: OS Independent
Classifier: Topic :: Scientific/Engineering :: Artificial Intelligence
Requires-Python: >=3.8
